docker_volume-0.4.post1.dist-info/DESCRIPTION.rst
docker_volume-0.4.post1.dist-info/METADATA
docker_volume-0.4.post1.dist-info/RECORD
docker_volume-0.4.post1.dist-info/WHEEL
docker_volume-0.4.post1.dist-info/entry_points.txt
docker_volume-0.4.post1.dist-info/metadata.json
docker_volume-0.4.post1.dist-info/namespace_packages.txt
docker_volume-0.4.post1.dist-info/top_level.txt
dockervolume/__init__.py
dockervolume/__main__.py
dockervolume/bootstraps.py
dockervolume/compat.py
dockervolume/core.py
dockervolume/exc.py
dockervolume/interfaces.py
dockervolume/log.py
dockervolume/operations.py
dockervolume/primitives.py
dockervolume/registries.py
dockervolume/settings.py
dockervolume/utils.py
dockervolume/volumes.py
dockervolume/commands/__init__.py
dockervolume/commands/add.py
dockervolume/commands/directory.py
dockervolume/commands/mount.py
dockervolume/commands/remove.py
dockervolume/commands/umount.py
dockervolume/commands/unmount.py
dockervolume/conf/README.rst
dockervolume/conf/log.ini
