Metadata-Version: 2.0
Name: docker-volume
Version: 0.4.post1
Summary: Management tool of VirtualBox Volume for Docker
Home-page: https://github.com/TakesxiSximada/docker-volume
Author: TakesxiSximada
Author-email: sximada@gmail.com
License: UNKNOWN
Download-URL: https://github.com/TakesxiSximada/docker-volume/archive/master.zip
Keywords: Docker,VirtualBox
Platform: UNKNOWN
Classifier: Programming Language :: Python
Requires-Dist: PyYAML
Requires-Dist: jumon
Requires-Dist: lazr.delegates
Requires-Dist: mako
Requires-Dist: six
Requires-Dist: zope.component
Requires-Dist: zope.interface
Provides-Extra: develop
Requires-Dist: wheel; extra == 'develop'
Provides-Extra: docs
Requires-Dist: sphinx; extra == 'docs'
Provides-Extra: testing
Requires-Dist: astroid; extra == 'testing'
Requires-Dist: detox; extra == 'testing'
Requires-Dist: eventlet; extra == 'testing'
Requires-Dist: flake8; extra == 'testing'
Requires-Dist: mypy-lang; extra == 'testing'
Requires-Dist: nose; extra == 'testing'
Requires-Dist: pylint; extra == 'testing'
Requires-Dist: selenium; extra == 'testing'
Requires-Dist: tox; extra == 'testing'
Requires-Dist: vulture; extra == 'testing'
